demo.py
zenity_wrapper.py
python_zenity_wrapper-0.1.0.dist-info/licenses/LICENSE
python_zenity_wrapper-0.1.0.dist-info/METADATA
python_zenity_wrapper-0.1.0.dist-info/WHEEL
python_zenity_wrapper-0.1.0.dist-info/entry_points.txt
python_zenity_wrapper-0.1.0.dist-info/top_level.txt
python_zenity_wrapper-0.1.0.dist-info/RECORD
