Metadata-Version: 2.4
Name: python-zenity-wrapper
Version: 0.1.0
Summary: A comprehensive Python wrapper for Zenity dialogs
Home-page: https://github.com/codecaine-zz/python_zenity_wrapper
Author: CodeCaine
Author-email: 
License: MIT
Project-URL: Homepage, https://github.com/codecaine-zz/python_zenity_wrapper
Project-URL: Repository, https://github.com/codecaine-zz/python_zenity_wrapper
Project-URL: Bug Reports, https://github.com/codecaine-zz/python_zenity_wrapper/issues
Keywords: zenity,dialog,gui,desktop,notification,wrapper,linux,macos
Classifier: Development Status :: 4 - Beta
Classifier: Intended Audience :: Developers
Classifier: Topic :: Software Development :: Libraries :: Python Modules
Classifier: Topic :: Software Development :: User Interfaces
Classifier: License :: OSI Approved :: MIT License
Classifier: Programming Language :: Python :: 3
Classifier: Programming Language :: Python :: 3.7
Classifier: Programming Language :: Python :: 3.8
Classifier: Programming Language :: Python :: 3.9
Classifier: Programming Language :: Python :: 3.10
Classifier: Programming Language :: Python :: 3.11
Classifier: Programming Language :: Python :: 3.12
Classifier: Operating System :: POSIX :: Linux
Classifier: Operating System :: MacOS :: MacOS X
Classifier: Environment :: X11 Applications
Requires-Python: >=3.7
License-File: LICENSE
Provides-Extra: dev
Requires-Dist: pytest>=7.0; extra == "dev"
Requires-Dist: pytest-cov>=4.0; extra == "dev"
Requires-Dist: black>=23.0; extra == "dev"
Requires-Dist: flake8>=6.0; extra == "dev"
Requires-Dist: mypy>=1.0; extra == "dev"
Dynamic: home-page
Dynamic: license-file
Dynamic: requires-python
